nalax/__init__.py
nalax/__main__.py
nalax/__version__.py
nalax-0.dist-info/entry_points.txt
nalax-0.dist-info/LICENSE
nalax-0.dist-info/WHEEL
nalax-0.dist-info/METADATA
nalax-0.dist-info/RECORD
